{
    "sample_count_12gb": {
        "0": 183997, 
        "1": 183951, 
        "2": 183910, 
        "3": 183969, 
        "4": 183964, 
        "5": 183964, 
        "6": 183960, 
        "7": 183987, 
        "8": 182873, 
        "9": 182833
    }, 
    "task_count_12gb": {
        "0": 13767, 
        "1": 13798, 
        "2": 13795, 
        "3": 13799, 
        "4": 13798, 
        "5": 13798, 
        "6": 13798, 
        "7": 13800, 
        "8": 13719, 
        "9": 13687
    }, 
    "task_count_12gb_ext": {
        "0": {
            "test": 146, 
            "train": 13767, 
            "validation": 145
        }, 
        "1": {
            "test": 145, 
            "train": 13798, 
            "validation": 155
        }, 
        "2": {
            "test": 155, 
            "train": 13795, 
            "validation": 150
        }, 
        "3": {
            "test": 150, 
            "train": 13799, 
            "validation": 151
        }, 
        "4": {
            "test": 151, 
            "train": 13798, 
            "validation": 146
        }, 
        "5": {
            "test": 146, 
            "train": 13798, 
            "validation": 150
        }, 
        "6": {
            "test": 150, 
            "train": 13798, 
            "validation": 150
        }, 
        "7": {
            "test": 150, 
            "train": 13800, 
            "validation": 146
        }, 
        "8": {
            "test": 146, 
            "train": 13719, 
            "validation": 153
        }, 
        "9": {
            "test": 153, 
            "train": 13687, 
            "validation": 146
        }
    }
}